pokedex_python/__init__.py
pokedex_python/pokédex.py
pokedex_python-0.0.3.dist-info/licenses/LICENSE.txt
pokedex_python-0.0.3.dist-info/METADATA
pokedex_python-0.0.3.dist-info/WHEEL
pokedex_python-0.0.3.dist-info/top_level.txt
pokedex_python-0.0.3.dist-info/RECORD
