Metadata-Version: 2.4
Name: pokedex_python
Version: 0.0.3
Summary: Simple Pokédex application in Python
Home-page: https://github.com/Ishan-Karpe/Pokedex
Author: Ishan Karpe
Author-email: ishan.k.abhijeet@gmail.com
License-File: LICENSE.txt
Dynamic: author
Dynamic: author-email
Dynamic: description
Dynamic: description-content-type
Dynamic: home-page
Dynamic: license-file
Dynamic: summary
